django_httpxforwardedfor-0.3.1.dist-info/DESCRIPTION.rst
django_httpxforwardedfor-0.3.1.dist-info/METADATA
django_httpxforwardedfor-0.3.1.dist-info/RECORD
django_httpxforwardedfor-0.3.1.dist-info/WHEEL
django_httpxforwardedfor-0.3.1.dist-info/metadata.json
django_httpxforwardedfor-0.3.1.dist-info/top_level.txt
httpxforwardedfor/__init__.py
httpxforwardedfor/middleware.py
