Metadata-Version: 2.0
Name: django-httpxforwardedfor
Version: 0.3.1
Summary: Set request.META['REMOTE_ADDR'] from request.META['HTTP_X_FORWARDED_FOR']
Home-page: https://github.com/PaesslerAG/django-httpxforwardedfor
Author: Paessler AG
Author-email: bis@paessler.com
License: BSD
Keywords: django-httpxforwardedfor
Platform: UNKNOWN
Classifier: Development Status :: 4 - Beta
Classifier: Intended Audience :: Developers
Classifier: License :: OSI Approved :: BSD License
Classifier: Natural Language :: English
Classifier: Programming Language :: Python :: 2
Classifier: Programming Language :: Python :: 2.7
Classifier: Programming Language :: Python :: 3
Classifier: Programming Language :: Python :: 3.5
Classifier: Programming Language :: Python :: 3.6
Classifier: Programming Language :: Python :: 3.7
Classifier: Framework :: Django
Classifier: Framework :: Django :: 1.11
Classifier: Framework :: Django :: 2.0
Classifier: Framework :: Django :: 2.1
Requires-Dist: Django (<=2.1,>=1.11)
Requires-Dist: IPy
